subsys_client/__init__.py
subsys_client-0.2.dist-info/METADATA
subsys_client-0.2.dist-info/WHEEL
subsys_client-0.2.dist-info/top_level.txt
subsys_client-0.2.dist-info/RECORD
